{
    "variants": {
        "extended=false,facing=down": { "model": "mazetowers:memory_piston", "x": 90 },
        "extended=false,facing=up": { "model": "mazetowers:memory_piston", "x": 270 },
        "extended=false,facing=north": { "model": "mazetowers:memory_piston" },
        "extended=false,facing=south": { "model": "mazetowers:memory_piston", "y": 180 },
        "extended=false,facing=west": { "model": "mazetowers:memory_piston", "y": 270 },
        "extended=false,facing=east": { "model": "mazetowers:memory_piston", "y": 90 },
        "extended=true,facing=down": { "model": "mazetowers:memory_piston_extended", "x": 90 },
        "extended=true,facing=up": { "model": "mazetowers:memory_piston_extended", "x": 270 },
        "extended=true,facing=north": { "model": "mazetowers:memory_piston_extended" },
        "extended=true,facing=south": { "model": "mazetowers:memory_piston_extended", "y": 180 },
        "extended=true,facing=west": { "model": "mazetowers:memory_piston_extended", "y": 270 },
        "extended=true,facing=east": { "model": "mazetowers:memory_piston_extended", "y": 90 }
    }
}
